easysms
