Metadata-Version: 1.1
Name: easysms
Version: 0.0.2
Summary: The EasySMS is a python wrapper for Easy SMS API. Currently Easy SMS API available as a Heroku add-on Easy SMS only.
